snapstream/__init__.py
snapstream/__main__.py
snapstream/caching.py
snapstream/codecs.py
snapstream/core.py
snapstream/utils.py
snapstream-1.0.0.dist-info/LICENSE
snapstream-1.0.0.dist-info/METADATA
snapstream-1.0.0.dist-info/WHEEL
snapstream-1.0.0.dist-info/entry_points.txt
snapstream-1.0.0.dist-info/RECORD
