Metadata-Version: 2.1
Name: snapstream
Version: 1.0.0
Summary: Streamline your Kafka data processing, this tool aims to standardize streaming data from multiple Kafka clusters. With a pub-sub approach, multiple functions can easily subscribe to incoming messages, serialization can be specified per topic, and data is automatically processed by data sink functions.
Home-page: https://github.com/Menziess/snapstream
License: MIT
Keywords: kafka,pubsub
Author: Menziess
Author-email: stefan_schenk@hotmail.com
Requires-Python: >=3.8.1,<4.0.0
Classifier: Development Status :: 4 - Beta
Classifier: Intended Audience :: Developers
Classifier: Intended Audience :: Science/Research
Classifier: License :: OSI Approved :: MIT License
Classifier: Programming Language :: Python :: 3
Classifier: Programming Language :: Python :: 3.9
Classifier: Programming Language :: Python :: 3.10
Classifier: Programming Language :: Python :: 3.11
Classifier: Programming Language :: Python :: 3
Classifier: Programming Language :: Python :: 3.10
Classifier: Programming Language :: Python :: 3.8
Classifier: Programming Language :: Python :: 3.9
Classifier: Topic :: Scientific/Engineering
Classifier: Topic :: Scientific/Engineering :: Artificial Intelligence
Requires-Dist: avro (>=1.11.1,<2.0.0)
Requires-Dist: confluent-kafka (>=2.0.2,<3.0.0)
Requires-Dist: pypubsub (>=4.0.3,<5.0.0)
Requires-Dist: pyright (>=1.1.302,<2.0.0)
Requires-Dist: rocksdict (>=0.3.10,<0.4.0)
Requires-Dist: toolz (>=0.12.0,<0.13.0)
Project-URL: Documentation, https://snapstream.readthedocs.io
Project-URL: Repository, https://github.com/Menziess/snapstream
